fabric_cf/Design.md
fabric_cf/__init__.py
fabric_cf/actor/__init__.py
fabric_cf/actor/boot/__init__.py
fabric_cf/actor/boot/configuration.py
fabric_cf/actor/boot/configuration_exception.py
fabric_cf/actor/boot/configuration_loader.py
fabric_cf/actor/boot/configuration_processor.py
fabric_cf/actor/boot/inventory/__init__.py
fabric_cf/actor/boot/inventory/aggregate_resource_model_creator.py
fabric_cf/actor/core/__init__.py
fabric_cf/actor/core/apis/__init__.py
fabric_cf/actor/core/apis/abc_actor_container.py
fabric_cf/actor/core/apis/abc_actor_event.py
fabric_cf/actor/core/apis/abc_actor_identity.py
fabric_cf/actor/core/apis/abc_actor_management_object.py
fabric_cf/actor/core/apis/abc_actor_mixin.py
fabric_cf/actor/core/apis/abc_actor_proxy.py
fabric_cf/actor/core/apis/abc_actor_runnable.py
fabric_cf/actor/core/apis/abc_authority.py
fabric_cf/actor/core/apis/abc_authority_policy.py
fabric_cf/actor/core/apis/abc_authority_proxy.py
fabric_cf/actor/core/apis/abc_authority_reservation.py
fabric_cf/actor/core/apis/abc_base_plugin.py
fabric_cf/actor/core/apis/abc_broker_mixin.py
fabric_cf/actor/core/apis/abc_broker_policy_mixin.py
fabric_cf/actor/core/apis/abc_broker_proxy.py
fabric_cf/actor/core/apis/abc_broker_reservation.py
fabric_cf/actor/core/apis/abc_callback_proxy.py
fabric_cf/actor/core/apis/abc_client_actor.py
fabric_cf/actor/core/apis/abc_client_actor_management_object.py
fabric_cf/actor/core/apis/abc_client_callback_proxy.py
fabric_cf/actor/core/apis/abc_client_policy.py
fabric_cf/actor/core/apis/abc_client_reservation.py
fabric_cf/actor/core/apis/abc_component.py
fabric_cf/actor/core/apis/abc_concrete_set.py
fabric_cf/actor/core/apis/abc_container_clock.py
fabric_cf/actor/core/apis/abc_container_database.py
fabric_cf/actor/core/apis/abc_controller.py
fabric_cf/actor/core/apis/abc_controller_callback_proxy.py
fabric_cf/actor/core/apis/abc_controller_policy.py
fabric_cf/actor/core/apis/abc_controller_reservation.py
fabric_cf/actor/core/apis/abc_database.py
fabric_cf-1.9.1.dist-info/licenses/LICENSE
fabric_cf-1.9.1.dist-info/WHEEL
fabric_cf-1.9.1.dist-info/METADATA
fabric_cf-1.9.1.dist-info/RECORD
