Metadata-Version: 2.4
Name: fabric_cf
Version: 1.9.1
Summary: Fabric Control Framework
Keywords: Swagger,Fabric Control Framework
Author-email: Komal Thareja <kthare10@renci.org>, Ilya Baldin <ibaldin@renci.org>
Requires-Python: >=3.9
Classifier: Programming Language :: Python :: 3
Classifier: License :: OSI Approved :: MIT License
Classifier: Operating System :: OS Independent
License-File: LICENSE
Requires-Dist: requests >= 2.28.1
Requires-Dist: cryptography==43.0.3
Requires-Dist: psycopg2-binary
Requires-Dist: sqlalchemy
Requires-Dist: waitress
Requires-Dist: prometheus_client
Requires-Dist: connexion==2.14.2
Requires-Dist: swagger-ui-bundle==0.0.9
Requires-Dist: PyYAML
Requires-Dist: fabric_fss_utils==1.6.0
Requires-Dist: fabric-message-bus==1.9.0
Requires-Dist: fabric-fim==1.9.1
Requires-Dist: fabrictestbed==1.9.1
Requires-Dist: ansible
Requires-Dist: pytest ; extra == "test"
Requires-Dist: flask_testing ; extra == "test"
Requires-Dist: coverage>=4.0.3 ; extra == "test"
Requires-Dist: nose>=1.3.7 ; extra == "test"
Requires-Dist: pluggy>=0.3.1 ; extra == "test"
Requires-Dist: py>=1.4.31 ; extra == "test"
Requires-Dist: randomize>=0.13 ; extra == "test"
Project-URL: Home, https://fabric-testbed.net/
Project-URL: Sources, https://github.com/fabric-testbed/ControlFramework
Provides-Extra: test
